MANIFEST.in
setup.py
nginx_sites/__init__.py
nginx_sites/colorize.py
nginx_sites/nginx_sites.py
nginx_sites.egg-info/PKG-INFO
nginx_sites.egg-info/SOURCES.txt
nginx_sites.egg-info/dependency_links.txt
nginx_sites.egg-info/entry_points.txt
nginx_sites.egg-info/pbr.json
nginx_sites.egg-info/requires.txt
nginx_sites.egg-info/top_level.txt
nginx_sites/templates/apache.conf
nginx_sites/templates/laravel-php5.conf
nginx_sites/templates/laravel-php7.conf
nginx_sites/templates/node.conf
nginx_sites/templates/php.conf
nginx_sites/templates/python.conf
nginx_sites/templates/static.conf