Metadata-Version: 1.0
Name: nginx-sites
Version: 0.1.6
Summary: cli utility for managing nginx site configs
Home-page: https://github.com/zweifisch/nginx-sites
Author: Feng Zhou
Author-email: zf.pascal@gmail.com
License: UNKNOWN
Platform: UNKNOWN
